augmentit/__init__.py
augmentit/draw/__init__.py
augmentit/draw/plot_box.py
augmentit/formats/__init__.py
augmentit/formats/yolo.py
augmentit/segmentation/__init__.py
augmentit/segmentation/crop_image.py
augmentit/segmentation/resize_image.py
augmentit-1.0.3.dist-info/LICENSE.txt
augmentit-1.0.3.dist-info/METADATA
augmentit-1.0.3.dist-info/WHEEL
augmentit-1.0.3.dist-info/top_level.txt
augmentit-1.0.3.dist-info/RECORD
