Metadata-Version: 2.1
Name: augmentit
Version: 1.0.3
Summary: package to do some basic image augmentation for polygons and boxes.
Home-page: https://github.com/sandesha-hegde/augmentit.git
Author: Sandesh Hegde
Author-email: sandeshangiras@gmail.com
License: UNKNOWN
Platform: UNKNOWN
Classifier: Programming Language :: Python :: 3
Classifier: Operating System :: OS Independent
Requires-Python: >=3.6
Requires-Dist: opencv-python (==4.5.1.48)
Requires-Dist: numpy (~=1.19.2)
Requires-Dist: augmentit (~=1.0.1)
Requires-Dist: setuptools (~=52.0.0)
